belt_nlp/__init__.py
belt_nlp/bert.py
belt_nlp/bert_classifier_truncated.py
belt_nlp/bert_classifier_with_pooling.py
belt_nlp/bert_regressor_truncated.py
belt_nlp/bert_regressor_with_pooling.py
belt_nlp/bert_truncated.py
belt_nlp/bert_with_pooling.py
belt_nlp/exceptions.py
belt_nlp/splitting.py
belt_nlp/tensor_utils.py
belt_nlp-1.1.0.dist-info/LICENSE.txt
belt_nlp-1.1.0.dist-info/METADATA
belt_nlp-1.1.0.dist-info/WHEEL
belt_nlp-1.1.0.dist-info/top_level.txt
belt_nlp-1.1.0.dist-info/RECORD
