Metadata-Version: 2.1
Name: belt_nlp
Version: 1.1.0
Summary: BELT (BERT For Longer Texts). BERT-based text classification model for processing texts longer than 512 tokens.
Author-email: Michał Brzozowski <michal.brzozowski@mim.ai>, Marek Wachnicki <marek.wachnicki@mim.ai>
Project-URL: Homepage, https://github.com/mim-solutions/bert_for_longer_texts
Project-URL: Bug Tracker, https://github.com/mim-solutions/bert_for_longer_texts/issues
Keywords: nlp,natural-language-processing,text-classification,transformers,transfer-learning,bert,pytorch,machine-learning,deep-learning,roberta
Classifier: Programming Language :: Python :: 3
Classifier: License :: OSI Approved :: MIT License
Classifier: Operating System :: OS Independent
Requires-Python: >=3.9
License-File: LICENSE.txt
Requires-Dist: torch >=1.7.1
Requires-Dist: transformers >=4.8
